ansys/tools/repo_sync/__init__.py
ansys/tools/repo_sync/__main__.py
ansys/tools/repo_sync/constants.py
ansys/tools/repo_sync/repo_sync.py
ansys_tools_repo_sync-1.4.0.dist-info/entry_points.txt
ansys_tools_repo_sync-1.4.0.dist-info/licenses/LICENSE
ansys_tools_repo_sync-1.4.0.dist-info/WHEEL
ansys_tools_repo_sync-1.4.0.dist-info/METADATA
ansys_tools_repo_sync-1.4.0.dist-info/RECORD
