Metadata-Version: 2.4
Name: ansys-tools-repo-sync
Version: 1.4.0
Summary: Synchronize the content of two different repositories.
Author-email: "ANSYS, Inc." <pyansys.core@ansys.com>
Maintainer-email: "ANSYS, Inc." <pyansys.core@ansys.com>
Requires-Python: >=3.10,<4
Classifier: Development Status :: 4 - Beta
Classifier: Programming Language :: Python :: 3.10
Classifier: Programming Language :: Python :: 3.11
Classifier: Programming Language :: Python :: 3.12
Classifier: Programming Language :: Python :: 3.13
Classifier: License :: OSI Approved :: MIT License
Classifier: Operating System :: OS Independent
License-File: LICENSE
Requires-Dist: click>=8.0.4
Requires-Dist: PyGithub>=1.58
Requires-Dist: gitpython>=3.1
Requires-Dist: ansys-sphinx-theme[autoapi]==1.5.3 ; extra == "doc"
Requires-Dist: numpydoc==1.9.0 ; extra == "doc"
Requires-Dist: sphinx==8.2.3 ; extra == "doc"
Requires-Dist: sphinx-autodoc-typehints==3.1.0 ; extra == "doc"
Requires-Dist: sphinx-copybutton==0.5.2 ; extra == "doc"
Requires-Dist: pytest==8.4.1 ; extra == "tests"
Requires-Dist: pytest-cov==6.2.1 ; extra == "tests"
Requires-Dist: click==8.2.1 ; extra == "tests"
Requires-Dist: PyGithub==2.6.1 ; extra == "tests"
Requires-Dist: gitpython==3.1.44 ; extra == "tests"
Project-URL: Homepage, https://github.com/ansys/ansys-tools-repo-sync
Project-URL: Source, https://github.com/ansys/ansys-tools-repo-sync
Project-URL: Tracker, https://github.com/ansys/ansys-tools-repo-sync/issues
Provides-Extra: doc
Provides-Extra: tests
